bin/_extend_path.py
bin/html_table.py
bin/parallel_requests.py
bin/verify_server.py
examples/__init__.py
examples/_extend_path.py
examples/discoverable.py
examples/discoverable_with_oas.py
examples/filesystem.py
examples/object_parser.py
examples/rest_client_explicit.py
examples/rest_client_implicit.py
examples/server.py
examples/shell_example.py
mash/__main__.py
mash/cli.py
mash/doc_inference.py
mash/io_util.py
mash/progress_bar.py
mash/subshell.py
mash/util.py
mash/filesystem/__init__.py
mash/filesystem/discoverable.py
mash/filesystem/filesystem.py
mash/filesystem/scope.py
mash/filesystem/view.py
mash/object_parser/__init__.py
mash/object_parser/errors.py
mash/object_parser/factory.py
mash/object_parser/oas.py
mash/object_parser/object_parser.py
mash/object_parser/object_parser_standards.py
mash/server/__init__.py
mash/server/repository.py
mash/server/server.py
mash/server/domain/__init__.py
mash/server/domain/css.py
mash/server/domain/user.py
mash/server/routes/__init__.py
mash/server/routes/default.py
mash/server/routes/documents.py
mash/server/routes/users.py
mash/shell/__init__.py
mash/shell/base.py
mash/shell/cmd2.py
mash/shell/errors.py
mash/shell/function.py
mash/shell/shell.py
mash/shell/with_filesystem.py
mash/shell/ast/__init__.py
mash/shell/ast/conditions.py
mash/shell/ast/function_definition.py
mash/shell/ast/infix.py
mash/shell/ast/node.py
mash/shell/ast/nodes.py
mash/shell/ast/set_definition.py
mash/shell/ast/term.py
mash/shell/grammer/__init__.py
mash/shell/grammer/literals.py
mash/shell/grammer/parse_functions.py
mash/shell/grammer/parser.py
mash/shell/grammer/tokenizer.py
mash/shell/internals/helpers.py
mash/shell/internals/if_statement.py
mash/webtools/__init__.py
mash/webtools/html_table.py
mash/webtools/html_table_data.py
mash/webtools/parallel.py
mash/webtools/parallel_requests.py
mash/webtools/pipeline.py
mash/webtools/verify_server.py
mash_shell-0.2.15.dist-info/licenses/LICENSE
mash_shell-0.2.15.dist-info/METADATA
mash_shell-0.2.15.dist-info/WHEEL
mash_shell-0.2.15.dist-info/top_level.txt
mash_shell-0.2.15.dist-info/RECORD
