Metadata-Version: 2.4
Name: mash-shell
Version: 0.2.15
Summary: A shell and other utils
Author-email: voschezang <mark.voschezang@student.uva.nl>
Project-URL: Homepage, https://github.com/voschezang/mash
Project-URL: Bug Tracker, https://github.com/voschezang/mash/issues
Classifier: Programming Language :: Python :: 3
Classifier: Topic :: System :: Shells
Classifier: License :: OSI Approved :: GNU General Public License v3 (GPLv3)
Classifier: Operating System :: OS Independent
Requires-Python: >=3.8
License-File: LICENSE
Requires-Dist: aiohttp
Requires-Dist: autopep8
Requires-Dist: braceexpand
Requires-Dist: django
Requires-Dist: dominate
Requires-Dist: flake8
Requires-Dist: flask
Requires-Dist: mistletoe
Requires-Dist: pandas
Requires-Dist: ply
Requires-Dist: pytest
Requires-Dist: pytest-cov
Requires-Dist: pytest-xdist
Requires-Dist: pyyaml
Requires-Dist: quo==2022.8.2
Requires-Dist: rich
Requires-Dist: requests
Requires-Dist: scipy
Requires-Dist: tabulate
Requires-Dist: termcolor
Dynamic: license-file
